Pylette/__init__.py
Pylette/cmd.py
Pylette/py.typed
Pylette/types.py
Pylette/src/__init__.py
Pylette/src/cli_utils.py
Pylette/src/color.py
Pylette/src/color_extraction.py
Pylette/src/palette.py
Pylette/src/types.py
Pylette/src/extractors/k_means.py
Pylette/src/extractors/median_cut.py
Pylette/src/extractors/protocol.py
pylette-5.1.1.dist-info/METADATA
pylette-5.1.1.dist-info/WHEEL
pylette-5.1.1.dist-info/entry_points.txt
pylette-5.1.1.dist-info/licenses/LICENSE.md
pylette-5.1.1.dist-info/RECORD
