Metadata-Version: 2.4
Name: pylette
Version: 5.1.1
Summary: A Python library for extracting color palettes from images.
Author: Ivar Stangeby
License: MIT
License-File: LICENSE.md
Classifier: Development Status :: 5 - Production/Stable
Classifier: Intended Audience :: Developers
Classifier: License :: OSI Approved :: MIT License
Classifier: Programming Language :: Python :: 3
Classifier: Programming Language :: Python :: 3.10
Classifier: Programming Language :: Python :: 3.11
Classifier: Programming Language :: Python :: 3.12
Classifier: Programming Language :: Python :: 3.13
Classifier: Typing :: Typed
Requires-Python: >=3.10
Requires-Dist: numpy>=1.26.4
Requires-Dist: opencv-python>=4.11.0.86
Requires-Dist: pillow<11.0,>=9.3
Requires-Dist: requests>=2.32.3
Requires-Dist: scikit-learn>=1.2
Requires-Dist: typer>=0.12.5
Provides-Extra: dev
Requires-Dist: mkdocs-glightbox>=0.4.0; extra == 'dev'
Requires-Dist: mkdocs-material>=9.5.27; extra == 'dev'
Requires-Dist: mkdocs[python]>=1.6.0; extra == 'dev'
Requires-Dist: mkdocstrings[python]>=0.25.1; extra == 'dev'
Requires-Dist: opencv-python>=4.10.0.84; extra == 'dev'
Requires-Dist: pre-commit>=3.7.1; extra == 'dev'
Requires-Dist: pyright>=1.1.0; extra == 'dev'
Requires-Dist: pytest>=8.2.2; extra == 'dev'
Requires-Dist: requests-mock>=1.12.1; extra == 'dev'
Requires-Dist: ruff>=0.5.0; extra == 'dev'
